<annotation>
	<folder>Striploin</folder>
	<filename>20210406_085611_90.jpg</filename>
	<path>/media/pk/Data/Project/dataset/Meat_image/Greenham/meat_category/part2/JPEGImages/20210406_085611_90.jpg</path>
	<source>
		<database>Unknown</database>
	</source>
	<size>
		<width>1080</width>
		<height>1920</height>
		<depth>3</depth>
	</size>
	<segmented>0</segmented>
	<object>
		<name>Striploin</name>
		<pose>Unspecified</pose>
		<truncated>0</truncated>
		<difficult>0</difficult>
		<bndbox>
			<xmin>551</xmin>
			<ymin>752</ymin>
			<xmax>854</xmax>
			<ymax>1599</ymax>
		</bndbox>
	</object>
	<object>
		<name>Striploin</name>
		<pose>Unspecified</pose>
		<truncated>0</truncated>
		<difficult>0</difficult>
		<bndbox>
			<xmin>439</xmin>
			<ymin>752</ymin>
			<xmax>726</xmax>
			<ymax>1654</ymax>
		</bndbox>
	</object>
	<object>
		<name>Striploin</name>
		<pose>Unspecified</pose>
		<truncated>0</truncated>
		<difficult>0</difficult>
		<bndbox>
			<xmin>283</xmin>
			<ymin>720</ymin>
			<xmax>520</xmax>
			<ymax>1641</ymax>
		</bndbox>
	</object>
	<object>
		<name>Striploin</name>
		<pose>Unspecified</pose>
		<truncated>0</truncated>
		<difficult>0</difficult>
		<bndbox>
			<xmin>173</xmin>
			<ymin>756</ymin>
			<xmax>392</xmax>
			<ymax>1667</ymax>
		</bndbox>
	</object>
</annotation>