<annotation>
	<folder>Striploin</folder>
	<filename>20210331_073444_49.jpg</filename>
	<path>/home/pk/Desktop/Github_project/BLV/Meat_type_Identification/data/V4/JPEGImages/20210331_073444_49.jpg</path>
	<source>
		<database>Unknown</database>
	</source>
	<size>
		<width>1920</width>
		<height>1080</height>
		<depth>3</depth>
	</size>
	<segmented>0</segmented>
	<object>
		<name>Striploin</name>
		<pose>Unspecified</pose>
		<truncated>0</truncated>
		<difficult>0</difficult>
		<bndbox>
			<xmin>677</xmin>
			<ymin>238</ymin>
			<xmax>1590</xmax>
			<ymax>649</ymax>
		</bndbox>
	</object>
	<object>
		<name>Striploin</name>
		<pose>Unspecified</pose>
		<truncated>0</truncated>
		<difficult>0</difficult>
		<bndbox>
			<xmin>621</xmin>
			<ymin>399</ymin>
			<xmax>1624</xmax>
			<ymax>707</ymax>
		</bndbox>
	</object>
	<object>
		<name>Striploin</name>
		<pose>Unspecified</pose>
		<truncated>0</truncated>
		<difficult>0</difficult>
		<bndbox>
			<xmin>803</xmin>
			<ymin>589</ymin>
			<xmax>1611</xmax>
			<ymax>695</ymax>
		</bndbox>
	</object>
	<object>
		<name>Striploin</name>
		<pose>Unspecified</pose>
		<truncated>0</truncated>
		<difficult>0</difficult>
		<bndbox>
			<xmin>713</xmin>
			<ymin>637</ymin>
			<xmax>1610</xmax>
			<ymax>908</ymax>
		</bndbox>
	</object>
</annotation>