<annotation>
	<folder>Cuberoll</folder>
	<filename>20210323_131900_146.jpg</filename>
	<path>/home/pk/Desktop/Github_project/BLV/Meat_type_Identification/data/V4/JPEGImages/20210323_131900_146.jpg</path>
	<source>
		<database>Unknown</database>
	</source>
	<size>
		<width>1920</width>
		<height>1080</height>
		<depth>3</depth>
	</size>
	<segmented>0</segmented>
	<object>
		<name>Cuberoll</name>
		<pose>Unspecified</pose>
		<truncated>0</truncated>
		<difficult>0</difficult>
		<bndbox>
			<xmin>923</xmin>
			<ymin>482</ymin>
			<xmax>1563</xmax>
			<ymax>730</ymax>
		</bndbox>
	</object>
	<object>
		<name>Cuberoll</name>
		<pose>Unspecified</pose>
		<truncated>0</truncated>
		<difficult>0</difficult>
		<bndbox>
			<xmin>873</xmin>
			<ymin>436</ymin>
			<xmax>1540</xmax>
			<ymax>580</ymax>
		</bndbox>
	</object>
	<object>
		<name>Cuberoll</name>
		<pose>Unspecified</pose>
		<truncated>0</truncated>
		<difficult>0</difficult>
		<bndbox>
			<xmin>875</xmin>
			<ymin>240</ymin>
			<xmax>1502</xmax>
			<ymax>459</ymax>
		</bndbox>
	</object>
	<object>
		<name>Cuberoll</name>
		<pose>Unspecified</pose>
		<truncated>0</truncated>
		<difficult>0</difficult>
		<bndbox>
			<xmin>759</xmin>
			<ymin>105</ymin>
			<xmax>1473</xmax>
			<ymax>282</ymax>
		</bndbox>
	</object>
	<object>
		<name>Cuberoll</name>
		<pose>Unspecified</pose>
		<truncated>0</truncated>
		<difficult>0</difficult>
		<bndbox>
			<xmin>719</xmin>
			<ymin>170</ymin>
			<xmax>921</xmax>
			<ymax>786</ymax>
		</bndbox>
	</object>
	<object>
		<name>Cuberoll</name>
		<pose>Unspecified</pose>
		<truncated>0</truncated>
		<difficult>0</difficult>
		<bndbox>
			<xmin>569</xmin>
			<ymin>115</ymin>
			<xmax>744</xmax>
			<ymax>734</ymax>
		</bndbox>
	</object>
</annotation>