<annotation>
	<folder>Chuckroll</folder>
	<filename>20210325_105549_167.jpg</filename>
	<path>/home/pk/Desktop/Github_project/BLV/Meat_type_Identification/data/V4/JPEGImages/20210325_105549_167.jpg</path>
	<source>
		<database>Unknown</database>
	</source>
	<size>
		<width>1920</width>
		<height>1080</height>
		<depth>3</depth>
	</size>
	<segmented>0</segmented>
	<object>
		<name>Chuckroll</name>
		<pose>Unspecified</pose>
		<truncated>0</truncated>
		<difficult>0</difficult>
		<bndbox>
			<xmin>688</xmin>
			<ymin>259</ymin>
			<xmax>1480</xmax>
			<ymax>657</ymax>
		</bndbox>
	</object>
	<object>
		<name>Chuckroll</name>
		<pose>Unspecified</pose>
		<truncated>0</truncated>
		<difficult>0</difficult>
		<bndbox>
			<xmin>609</xmin>
			<ymin>457</ymin>
			<xmax>1398</xmax>
			<ymax>880</ymax>
		</bndbox>
	</object>
</annotation>