<annotation>
	<folder>Striploin</folder>
	<filename>20210408_100423_20.jpg</filename>
	<path>/media/pk/Data/Project/dataset/Meat_image/Greenham/meat_category/part2/JPEGImages/20210408_100423_20.jpg</path>
	<source>
		<database>Unknown</database>
	</source>
	<size>
		<width>1080</width>
		<height>1920</height>
		<depth>3</depth>
	</size>
	<segmented>0</segmented>
	<object>
		<name>Striploin</name>
		<pose>Unspecified</pose>
		<truncated>0</truncated>
		<difficult>0</difficult>
		<bndbox>
			<xmin>476</xmin>
			<ymin>653</ymin>
			<xmax>754</xmax>
			<ymax>1638</ymax>
		</bndbox>
	</object>
	<object>
		<name>Striploin</name>
		<pose>Unspecified</pose>
		<truncated>0</truncated>
		<difficult>0</difficult>
		<bndbox>
			<xmin>318</xmin>
			<ymin>698</ymin>
			<xmax>543</xmax>
			<ymax>1477</ymax>
		</bndbox>
	</object>
	<object>
		<name>Striploin</name>
		<pose>Unspecified</pose>
		<truncated>0</truncated>
		<difficult>0</difficult>
		<bndbox>
			<xmin>151</xmin>
			<ymin>792</ymin>
			<xmax>509</xmax>
			<ymax>1663</ymax>
		</bndbox>
	</object>
	<object>
		<name>Striploin</name>
		<pose>Unspecified</pose>
		<truncated>0</truncated>
		<difficult>0</difficult>
		<bndbox>
			<xmin>57</xmin>
			<ymin>820</ymin>
			<xmax>223</xmax>
			<ymax>1574</ymax>
		</bndbox>
	</object>
</annotation>