<annotation>
	<folder>Tenderloin</folder>
	<filename>20210326_122823_129.jpg</filename>
	<path>/home/pk/Desktop/Github_project/BLV/Meat_type_Identification/data/V4/JPEGImages/20210326_122823_129.jpg</path>
	<source>
		<database>Unknown</database>
	</source>
	<size>
		<width>1920</width>
		<height>1080</height>
		<depth>3</depth>
	</size>
	<segmented>0</segmented>
	<object>
		<name>Tenderloin</name>
		<pose>Unspecified</pose>
		<truncated>0</truncated>
		<difficult>0</difficult>
		<bndbox>
			<xmin>857</xmin>
			<ymin>609</ymin>
			<xmax>1563</xmax>
			<ymax>847</ymax>
		</bndbox>
	</object>
	<object>
		<name>Tenderloin</name>
		<pose>Unspecified</pose>
		<truncated>0</truncated>
		<difficult>0</difficult>
		<bndbox>
			<xmin>607</xmin>
			<ymin>503</ymin>
			<xmax>1302</xmax>
			<ymax>872</ymax>
		</bndbox>
	</object>
	<object>
		<name>Tenderloin</name>
		<pose>Unspecified</pose>
		<truncated>0</truncated>
		<difficult>0</difficult>
		<bndbox>
			<xmin>961</xmin>
			<ymin>461</ymin>
			<xmax>1598</xmax>
			<ymax>703</ymax>
		</bndbox>
	</object>
	<object>
		<name>Tenderloin</name>
		<pose>Unspecified</pose>
		<truncated>0</truncated>
		<difficult>0</difficult>
		<bndbox>
			<xmin>638</xmin>
			<ymin>236</ymin>
			<xmax>1430</xmax>
			<ymax>555</ymax>
		</bndbox>
	</object>
	<object>
		<name>Tenderloin</name>
		<pose>Unspecified</pose>
		<truncated>0</truncated>
		<difficult>0</difficult>
		<bndbox>
			<xmin>817</xmin>
			<ymin>203</ymin>
			<xmax>1634</xmax>
			<ymax>474</ymax>
		</bndbox>
	</object>
</annotation>