<annotation>
	<folder>Striploin01</folder>
	<filename>20210323_094005_176.jpg</filename>
	<path>/home/pk/Desktop/Github_project/BLV/Meat_type_Identification/data/V4/JPEGImages/20210323_094005_176.jpg</path>
	<source>
		<database>Unknown</database>
	</source>
	<size>
		<width>1920</width>
		<height>1080</height>
		<depth>3</depth>
	</size>
	<segmented>0</segmented>
	<object>
		<name>Striploin</name>
		<pose>Unspecified</pose>
		<truncated>0</truncated>
		<difficult>0</difficult>
		<bndbox>
			<xmin>544</xmin>
			<ymin>43</ymin>
			<xmax>1463</xmax>
			<ymax>301</ymax>
		</bndbox>
	</object>
	<object>
		<name>Striploin</name>
		<pose>Unspecified</pose>
		<truncated>0</truncated>
		<difficult>0</difficult>
		<bndbox>
			<xmin>602</xmin>
			<ymin>243</ymin>
			<xmax>1419</xmax>
			<ymax>468</ymax>
		</bndbox>
	</object>
	<object>
		<name>Striploin</name>
		<pose>Unspecified</pose>
		<truncated>0</truncated>
		<difficult>0</difficult>
		<bndbox>
			<xmin>605</xmin>
			<ymin>309</ymin>
			<xmax>1605</xmax>
			<ymax>574</ymax>
		</bndbox>
	</object>
	<object>
		<name>Striploin</name>
		<pose>Unspecified</pose>
		<truncated>0</truncated>
		<difficult>0</difficult>
		<bndbox>
			<xmin>750</xmin>
			<ymin>536</ymin>
			<xmax>1640</xmax>
			<ymax>709</ymax>
		</bndbox>
	</object>
</annotation>