<annotation>
	<folder>Rump</folder>
	<filename>20210324_062603_59.jpg</filename>
	<path>/home/pk/Desktop/Github_project/BLV/Meat_type_Identification/data/V4/JPEGImages/20210324_062603_59.jpg</path>
	<source>
		<database>Unknown</database>
	</source>
	<size>
		<width>1920</width>
		<height>1080</height>
		<depth>3</depth>
	</size>
	<segmented>0</segmented>
	<object>
		<name>Rump</name>
		<pose>Unspecified</pose>
		<truncated>0</truncated>
		<difficult>0</difficult>
		<bndbox>
			<xmin>1130</xmin>
			<ymin>70</ymin>
			<xmax>1630</xmax>
			<ymax>707</ymax>
		</bndbox>
	</object>
	<object>
		<name>Rump</name>
		<pose>Unspecified</pose>
		<truncated>0</truncated>
		<difficult>0</difficult>
		<bndbox>
			<xmin>863</xmin>
			<ymin>101</ymin>
			<xmax>1284</xmax>
			<ymax>726</ymax>
		</bndbox>
	</object>
	<object>
		<name>Rump</name>
		<pose>Unspecified</pose>
		<truncated>0</truncated>
		<difficult>0</difficult>
		<bndbox>
			<xmin>580</xmin>
			<ymin>109</ymin>
			<xmax>1023</xmax>
			<ymax>726</ymax>
		</bndbox>
	</object>
</annotation>