<annotation>
	<folder>Cuberoll origin</folder>
	<filename>20210409_071859_75.jpg</filename>
	<path>/media/pk/Data/Project/dataset/Meat_image/Greenham/meat_category/part2/JPEGImages/20210409_071859_75.jpg</path>
	<source>
		<database>Unknown</database>
	</source>
	<size>
		<width>1080</width>
		<height>1920</height>
		<depth>3</depth>
	</size>
	<segmented>0</segmented>
	<object>
		<name>Cuberoll</name>
		<pose>Unspecified</pose>
		<truncated>0</truncated>
		<difficult>0</difficult>
		<bndbox>
			<xmin>198</xmin>
			<ymin>706</ymin>
			<xmax>476</xmax>
			<ymax>1638</ymax>
		</bndbox>
	</object>
	<object>
		<name>Cuberoll</name>
		<pose>Unspecified</pose>
		<truncated>0</truncated>
		<difficult>0</difficult>
		<bndbox>
			<xmin>420</xmin>
			<ymin>667</ymin>
			<xmax>676</xmax>
			<ymax>1616</ymax>
		</bndbox>
	</object>
	<object>
		<name>Cuberoll</name>
		<pose>Unspecified</pose>
		<truncated>0</truncated>
		<difficult>0</difficult>
		<bndbox>
			<xmin>601</xmin>
			<ymin>717</ymin>
			<xmax>834</xmax>
			<ymax>1668</ymax>
		</bndbox>
	</object>
</annotation>