<annotation>
	<folder>Striploin</folder>
	<filename>20210406_110548_46.jpg</filename>
	<path>/media/pk/Data/Project/dataset/Meat_image/Greenham/meat_category/part2/JPEGImages/20210406_110548_46.jpg</path>
	<source>
		<database>Unknown</database>
	</source>
	<size>
		<width>1080</width>
		<height>1920</height>
		<depth>3</depth>
	</size>
	<segmented>0</segmented>
	<object>
		<name>Striploin</name>
		<pose>Unspecified</pose>
		<truncated>0</truncated>
		<difficult>0</difficult>
		<bndbox>
			<xmin>702</xmin>
			<ymin>760</ymin>
			<xmax>917</xmax>
			<ymax>1637</ymax>
		</bndbox>
	</object>
	<object>
		<name>Striploin</name>
		<pose>Unspecified</pose>
		<truncated>0</truncated>
		<difficult>0</difficult>
		<bndbox>
			<xmin>603</xmin>
			<ymin>782</ymin>
			<xmax>805</xmax>
			<ymax>1711</ymax>
		</bndbox>
	</object>
	<object>
		<name>Striploin</name>
		<pose>Unspecified</pose>
		<truncated>0</truncated>
		<difficult>0</difficult>
		<bndbox>
			<xmin>485</xmin>
			<ymin>628</ymin>
			<xmax>658</xmax>
			<ymax>1735</ymax>
		</bndbox>
	</object>
	<object>
		<name>Striploin</name>
		<pose>Unspecified</pose>
		<truncated>0</truncated>
		<difficult>0</difficult>
		<bndbox>
			<xmin>417</xmin>
			<ymin>663</ymin>
			<xmax>547</xmax>
			<ymax>1714</ymax>
		</bndbox>
	</object>
	<object>
		<name>Striploin</name>
		<pose>Unspecified</pose>
		<truncated>0</truncated>
		<difficult>0</difficult>
		<bndbox>
			<xmin>283</xmin>
			<ymin>648</ymin>
			<xmax>458</xmax>
			<ymax>1701</ymax>
		</bndbox>
	</object>
</annotation>