<annotation>
	<folder>Cuberoll</folder>
	<filename>20210330_092909_88.jpg</filename>
	<path>/home/pk/Desktop/Github_project/BLV/Meat_type_Identification/data/V4/JPEGImages/20210330_092909_88.jpg</path>
	<source>
		<database>Unknown</database>
	</source>
	<size>
		<width>1920</width>
		<height>1080</height>
		<depth>3</depth>
	</size>
	<segmented>0</segmented>
	<object>
		<name>Cuberoll</name>
		<pose>Unspecified</pose>
		<truncated>0</truncated>
		<difficult>0</difficult>
		<bndbox>
			<xmin>630</xmin>
			<ymin>584</ymin>
			<xmax>1453</xmax>
			<ymax>865</ymax>
		</bndbox>
	</object>
	<object>
		<name>Cuberoll</name>
		<pose>Unspecified</pose>
		<truncated>0</truncated>
		<difficult>0</difficult>
		<bndbox>
			<xmin>651</xmin>
			<ymin>422</ymin>
			<xmax>1450</xmax>
			<ymax>654</ymax>
		</bndbox>
	</object>
	<object>
		<name>Cuberoll</name>
		<pose>Unspecified</pose>
		<truncated>0</truncated>
		<difficult>0</difficult>
		<bndbox>
			<xmin>657</xmin>
			<ymin>217</ymin>
			<xmax>1471</xmax>
			<ymax>465</ymax>
		</bndbox>
	</object>
</annotation>