<annotation>
	<folder>Tenderloin</folder>
	<filename>20210326_071731_124.jpg</filename>
	<path>/home/pk/Desktop/Github_project/BLV/Meat_type_Identification/data/V4/JPEGImages/20210326_071731_124.jpg</path>
	<source>
		<database>Unknown</database>
	</source>
	<size>
		<width>1920</width>
		<height>1080</height>
		<depth>3</depth>
	</size>
	<segmented>0</segmented>
	<object>
		<name>Tenderloin</name>
		<pose>Unspecified</pose>
		<truncated>0</truncated>
		<difficult>0</difficult>
		<bndbox>
			<xmin>967</xmin>
			<ymin>420</ymin>
			<xmax>1646</xmax>
			<ymax>832</ymax>
		</bndbox>
	</object>
	<object>
		<name>Tenderloin</name>
		<pose>Unspecified</pose>
		<truncated>0</truncated>
		<difficult>0</difficult>
		<bndbox>
			<xmin>652</xmin>
			<ymin>361</ymin>
			<xmax>1365</xmax>
			<ymax>615</ymax>
		</bndbox>
	</object>
	<object>
		<name>Tenderloin</name>
		<pose>Unspecified</pose>
		<truncated>0</truncated>
		<difficult>0</difficult>
		<bndbox>
			<xmin>757</xmin>
			<ymin>211</ymin>
			<xmax>1559</xmax>
			<ymax>470</ymax>
		</bndbox>
	</object>
</annotation>