<annotation>
	<folder>Chuckroll</folder>
	<filename>20210331_122549_32.jpg</filename>
	<path>/media/pk/Data/Project/dataset/Meat_image/Greenham/meat_category/part2/JPEGImages/20210331_122549_32.jpg</path>
	<source>
		<database>Unknown</database>
	</source>
	<size>
		<width>1080</width>
		<height>1920</height>
		<depth>3</depth>
	</size>
	<segmented>0</segmented>
	<object>
		<name>Chuckroll</name>
		<pose>Unspecified</pose>
		<truncated>0</truncated>
		<difficult>0</difficult>
		<bndbox>
			<xmin>58</xmin>
			<ymin>1182</ymin>
			<xmax>752</xmax>
			<ymax>1709</ymax>
		</bndbox>
	</object>
	<object>
		<name>Chuckroll</name>
		<pose>Unspecified</pose>
		<truncated>0</truncated>
		<difficult>0</difficult>
		<bndbox>
			<xmin>256</xmin>
			<ymin>743</ymin>
			<xmax>716</xmax>
			<ymax>1257</ymax>
		</bndbox>
	</object>
	<object>
		<name>Chuckroll</name>
		<pose>Unspecified</pose>
		<truncated>0</truncated>
		<difficult>0</difficult>
		<bndbox>
			<xmin>12</xmin>
			<ymin>728</ymin>
			<xmax>350</xmax>
			<ymax>1272</ymax>
		</bndbox>
	</object>
</annotation>