<annotation>
	<folder>Rump origin</folder>
	<filename>20210408_085934_72.jpg</filename>
	<path>/media/pk/Data/Project/dataset/Meat_image/Greenham/meat_category/part2/JPEGImages/20210408_085934_72.jpg</path>
	<source>
		<database>Unknown</database>
	</source>
	<size>
		<width>1080</width>
		<height>1920</height>
		<depth>3</depth>
	</size>
	<segmented>0</segmented>
	<object>
		<name>Rump</name>
		<pose>Unspecified</pose>
		<truncated>0</truncated>
		<difficult>0</difficult>
		<bndbox>
			<xmin>103</xmin>
			<ymin>663</ymin>
			<xmax>670</xmax>
			<ymax>1071</ymax>
		</bndbox>
	</object>
	<object>
		<name>Rump</name>
		<pose>Unspecified</pose>
		<truncated>0</truncated>
		<difficult>0</difficult>
		<bndbox>
			<xmin>178</xmin>
			<ymin>983</ymin>
			<xmax>758</xmax>
			<ymax>1334</ymax>
		</bndbox>
	</object>
	<object>
		<name>Rump</name>
		<pose>Unspecified</pose>
		<truncated>0</truncated>
		<difficult>0</difficult>
		<bndbox>
			<xmin>127</xmin>
			<ymin>1214</ymin>
			<xmax>767</xmax>
			<ymax>1643</ymax>
		</bndbox>
	</object>
</annotation>